aiowebhdfs/__init__.py
aiowebhdfs-0.0.2.dist-info/LICENSE
aiowebhdfs-0.0.2.dist-info/METADATA
aiowebhdfs-0.0.2.dist-info/WHEEL
aiowebhdfs-0.0.2.dist-info/top_level.txt
aiowebhdfs-0.0.2.dist-info/RECORD
