Metadata-Version: 2.1
Name: aiowebhdfs
Version: 0.0.2
Summary: A modern and asynchronous web client for WebHDFS
Home-page: https://github.com/canimus/aiowebhdfs
Author: Herminio Vazquez
Author-email: canimus@gmail.com
License: UNKNOWN
Platform: UNKNOWN
Classifier: Programming Language :: Python :: 3
Classifier: License :: OSI Approved :: GNU General Public License v3 (GPLv3)
Classifier: Operating System :: OS Independent
Classifier: Topic :: Internet :: WWW/HTTP
Classifier: Topic :: Internet :: WWW/HTTP :: Session
Classifier: Topic :: System :: Distributed Computing
Classifier: Topic :: System :: Filesystems
Classifier: Development Status :: 3 - Alpha
Requires-Python: >=3.6
Requires-Dist: aiofiles (==0.4.0)
Requires-Dist: aiohttp (==3.6.2)
Requires-Dist: asyncio (==3.4.3)
Requires-Dist: opnieuw (==0.0.3)
Requires-Dist: httpx (==0.11.1)
Requires-Dist: furl (==2.1.0)
